MANIFEST.in
license
readme.rst
setup.py
xo.py
exofrills.egg-info/PKG-INFO
exofrills.egg-info/SOURCES.txt
exofrills.egg-info/dependency_links.txt
exofrills.egg-info/entry_points.txt
exofrills.egg-info/not-zip-safe
exofrills.egg-info/requires.txt
exofrills.egg-info/top_level.txt
xontrib/xo.py