Metadata-Version: 1.1
Name: exofrills
Version: 0.1.13
Summary: exofrills text editor
Home-page: http://exofrills.org/
Author: Anthony Scopatz
Author-email: scopatz@gmail.com
License: UNKNOWN
Download-URL: https://github.com/scopatz/xo/zipball/0.1.13
Platform: UNKNOWN
Classifier: License :: OSI Approved
Classifier: Intended Audience :: Developers
Classifier: Programming Language :: Python :: 3
Classifier: Topic :: Utilities
Classifier: Topic :: Text Editors
